geolib/__init__.py
geolib/geohash.py
geolib-1.0.7.dist-info/LICENSE
geolib-1.0.7.dist-info/METADATA
geolib-1.0.7.dist-info/WHEEL
geolib-1.0.7.dist-info/top_level.txt
geolib-1.0.7.dist-info/RECORD
